bounded_zipf/__init__.py
bounded_zipf/zipf.py
bounded_zipf-1.0.0.dist-info/LICENSE
bounded_zipf-1.0.0.dist-info/METADATA
bounded_zipf-1.0.0.dist-info/WHEEL
bounded_zipf-1.0.0.dist-info/RECORD
