Metadata-Version: 2.1
Name: bounded-zipf
Version: 1.0.0
Summary: a bounded zipf generator ported from Go
Author: Yiling-J
Author-email: njjyl723@gmail.com
Requires-Python: >=3.7,<4.0
Classifier: Programming Language :: Python :: 3
Classifier: Programming Language :: Python :: 3.7
Classifier: Programming Language :: Python :: 3.8
Classifier: Programming Language :: Python :: 3.9
Classifier: Programming Language :: Python :: 3.10
Classifier: Programming Language :: Python :: 3.11
